README.md
setup.py
keras_squeezenet/__init__.py
keras_squeezenet/squeezenet.py
keras_squeezenet/version.py
keras_squeezenet.egg-info/PKG-INFO
keras_squeezenet.egg-info/SOURCES.txt
keras_squeezenet.egg-info/dependency_links.txt
keras_squeezenet.egg-info/not-zip-safe
keras_squeezenet.egg-info/requires.txt
keras_squeezenet.egg-info/top_level.txt