Metadata-Version: 1.0
Name: keras-squeezenet
Version: 0.4
Summary: Squeezenet implementation with Keras framework
Home-page: https://github.com/rcmalli/keras-squeezenet
Author: Refik Can MALLI
Author-email: mallir@itu.edu.tr
License: MIT
Platform: UNKNOWN
